 [
        {
         "Name": "Alekhya Ryali ",
         "Company": "TD Bank",
         "Role": "Data Analyst ",
         "Date": "December 19th,2022",
         "InternshipDuration": "8",
         "Intake": "Fall 2022"
        },
        {
         "Name": "Cecil Joseph ",
         "Company": "TD Bank",
         "Role": "Business System Analyst",
         "Date": "December 19th,2022",
         "InternshipDuration": "8",
         "Intake": "Fall 2022"
        },
        {
         "Name": "Anubhav Kumar Rajat ",
         "Company": "TD Bank",
         "Role": "Data Analyst ",
         "Date": "December 19th,2022",
         "InternshipDuration": "8",
         "Intake": "Fall 2022"
        },
        {
         "Name": "Dewanshi Yadav ",
         "Company": "TD Bank",
         "Role": "Software Engineer ",
         "Date": "December 19th,2022",
         "InternshipDuration": "8",
         "Intake": "Fall 2022"
        },
        {
         "Name": "Rachanben Tilva ",
         "Company": "TD Bank",
         "Role": "Data Analyst",
         "Date": "December 19th,2022",
         "InternshipDuration": "4",
         "Intake": "Fall 2022"
        },
        {
         "Name": "Hetvi Patel ",
         "Company": "TD Bank",
         "Role": "Quality Engineer",
         "Date": "December 19th,2022",
         "InternshipDuration": "4",
         "Intake": "Fall 2022"
        },
        {
         "Name": "Atharva Joshi ",
         "Company": "TD Bank",
         "Role": "Business System Analyst",
         "Date": "December 19th,2022",
         "InternshipDuration": "8",
         "Intake": "Fall 2022"
        },
        {
         "Name": "Aakash Ajaykumar Pandya ",
         "Company": "TD Bank",
         "Role": "Data Analyst Intern\/Co-op",
         "Date": "December 19th,2022",
         "InternshipDuration": "4",
         "Intake": "Fall 2022"
        },
        {
         "Name": "Rahil Shah ",
         "Company": "TD Bank",
         "Role": "Data Analyst Intern\/Co-op",
         "Date": "December 19th,2022",
         "InternshipDuration": "8",
         "Intake": "Fall 2022"
        },
        {
         "Name": "Avadh Patel ",
         "Company": "TD Bank",
         "Role": "Data Analyst Intern\/Co-op",
         "Date": "December 19th,2022",
         "InternshipDuration": "4",
         "Intake": "Fall 2022"
        },
        {
         "Name": "Jay Rikenhbhai Shah ",
         "Company": "TD Bank",
         "Role": "Data Analyst Intern\/Co-op",
         "Date": "December 19th,2022",
         "InternshipDuration": "4",
         "Intake": "Fall 2022"
        },
        {
         "Name": "Aneerban Chakraborty ",
         "Company": "TD Bank",
         "Role": "Data Analyst Intern\/Co-op",
         "Date": "December 19th,2022",
         "InternshipDuration": "8",
         "Intake": "Fall 2022"
        },
        {
         "Name": "Raj Patel ",
         "Company": "TD Bank",
         "Role": "Data Analyst Intern\/Co-op",
         "Date": "December 19th,2022",
         "InternshipDuration": "4",
         "Intake": "Fall 2022"
        },
        {
         "Name": "Pusti Thakkar ",
         "Company": "TD Bank",
         "Role": "Data Analyst Intern\/Co-op",
         "Date": "December 19th,2022",
         "InternshipDuration": "4",
         "Intake": "Fall 2022"
        },
        {
         "Name": "Jayadeepak Maddela ",
         "Company": "TD Bank",
         "Role": "Data Analyst Intern\/Co-op",
         "Date": "December 19th,2022",
         "InternshipDuration": "4",
         "Intake": "Fall 2022"
        },
        {
         "Name": "Parth Sanjaybhai Savani ",
         "Company": "TD Bank",
         "Role": "Data Analyst Intern\/Co-op",
         "Date": "December 19th,2022",
         "InternshipDuration": "4",
         "Intake": "Fall 2022"
        },
        {
         "Name": "Ishrak Tabassum Haque ",
         "Company": "TD Bank",
         "Role": "Data Analyst Intern\/Co-op",
         "Date": "December 19th,2022",
         "InternshipDuration": "8",
         "Intake": "Fall 2022"
        },
        {
         "Name": "Manak Rajeev Agarwal ",
         "Company": "TD Bank",
         "Role": "Data Analyst Intern\/Co-op",
         "Date": "December 19th,2022",
         "InternshipDuration": "8",
         "Intake": "Fall 2022"
        },
        {
         "Name": "Asrith Arutla ",
         "Company": "TD Bank",
         "Role": "Data Analyst Intern\/Co-op",
         "Date": "December 19th,2022",
         "InternshipDuration": "8",
         "Intake": "Fall 2022"
        },
        {
         "Name": "Kameswara Saidatta Srinivas Peddada ",
         "Company": "TD Bank",
         "Role": "Data Analyst Intern\/Co-op",
         "Date": "December 19th,2022",
         "InternshipDuration": "4",
         "Intake": "Fall 2022"
        },
        {
         "Name": "Yash Navneetbhai Bhalala ",
         "Company": "TD Bank",
         "Role": "Data Analyst Intern\/Co-op",
         "Date": "December 19th,2022",
         "InternshipDuration": "4",
         "Intake": "Fall 2022"
        },
        {
         "Name": "Ooha Boyalla ",
         "Company": "TD Bank",
         "Role": "Data Analyst Intern\/Co-op",
         "Date": "December 19th,2022",
         "InternshipDuration": "4",
         "Intake": "Fall 2022"
        },
        {
         "Name": "Parth Pandurang Awari ",
         "Company": "TD Bank",
         "Role": "Data Analyst Intern\/Co-op",
         "Date": "December 19th,2022",
         "InternshipDuration": "8",
         "Intake": "Fall 2022"
        },
        {
         "Name": "Prathyusha Madduri ",
         "Company": "TD Bank",
         "Role": "Data Analyst Intern\/Co-op",
         "Date": "December 19th,2022",
         "InternshipDuration": "4",
         "Intake": "Fall 2022"
        },
        {
         "Name": "Preet Amish Shah ",
         "Company": "TD Bank",
         "Role": "Data Analyst Intern\/Co-op",
         "Date": "December 19th,2022",
         "InternshipDuration": "8",
         "Intake": "Fall 2022"
        },
        {
         "Name": "Ronak Hareshbhai Navadiya ",
         "Company": "TD Bank",
         "Role": "Data Analyst Intern\/Co-op",
         "Date": "December 19th,2022",
         "InternshipDuration": "4",
         "Intake": "Fall 2022"
        },
        {
         "Name": "Fahad Talha Patel ",
         "Company": "TD Bank",
         "Role": "Data Analyst Intern\/Co-op",
         "Date": "December 19th,2022",
         "InternshipDuration": "4",
         "Intake": "Fall 2022"
        },
        {
         "Name": "Achyuth Balaji ",
         "Company": "TD Bank",
         "Role": "Data Analyst Intern\/Co-op",
         "Date": "December 19th,2022",
         "InternshipDuration": "8",
         "Intake": "Fall 2022"
        },
        {
         "Name": "Ahmed Mustafa ",
         "Company": "TD Bank",
         "Role": "Data Analyst Intern\/Co-op",
         "Date": "December 19th,2022",
         "InternshipDuration": "4",
         "Intake": "Fall 2022"
        },
        {
         "Name": "Juhil Muneshbhai Sangani ",
         "Company": "TD Bank",
         "Role": "Data Analyst Intern\/Co-op",
         "Date": "December 19th,2022",
         "InternshipDuration": "4",
         "Intake": "Fall 2022"
        },
        {
         "Name": "Varunkumar Patel ",
         "Company": "TD Bank",
         "Role": "Data Analyst Intern\/Co-op",
         "Date": "December 19th,2022",
         "InternshipDuration": "4",
         "Intake": "Fall 2022"
        },
        {
         "Name": "Dhruv Bhatt ",
         "Company": "TD Bank",
         "Role": "Data Analyst Intern\/Co-op",
         "Date": "December 19th,2022",
         "InternshipDuration": "4",
         "Intake": "Fall 2022"
        },
        {
         "Name": "Venkata Varaha Rama",
         "Company": "TD Bank",
         "Role": "Data Analyst Intern\/Co-op",
         "Date": "December 19th,2022",
         "InternshipDuration": "4",
         "Intake": "Fall 2022"
        },
        {
         "Name": "Vrushit Nileshkumar Bharucha ",
         "Company": "TD Bank",
         "Role": "Data Analyst Intern\/Co-op",
         "Date": "December 19th,2022",
         "InternshipDuration": "8",
         "Intake": "Fall 2022"
        },
        {
         "Name": "Sudhanshu Parhar ",
         "Company": "TD Bank",
         "Role": "Data Analyst Intern\/Co-op",
         "Date": "December 19th,2022",
         "InternshipDuration": "8",
         "Intake": "Fall 2022"
        },
        {
         "Name": "Mehul Jethva ",
         "Company": "TD Bank",
         "Role": "Data Analyst Intern\/Co-op",
         "Date": "December 19th,2022",
         "InternshipDuration": "4",
         "Intake": "Fall 2022"
        },
        {
         "Name": "Sanatkumar Dhobi ",
         "Company": "TD Bank",
         "Role": "Data Analyst Intern\/Co-op",
         "Date": "December 19th,2022",
         "InternshipDuration": "8",
         "Intake": "Fall 2022"
        },
        {
         "Name": "Sanket Pravinkumar ",
         "Company": "TD Bank",
         "Role": "Data Analyst Intern\/Co-op",
         "Date": "December 19th,2022",
         "InternshipDuration": "8",
         "Intake": "Fall 2022"
        },
        {
         "Name": "Simrandeep Singh ",
         "Company": "TD Bank",
         "Role": "Data Analyst Intern\/Co-op",
         "Date": "December 19th,2022",
         "InternshipDuration": "8",
         "Intake": "Fall 2022"
        },
        {
         "Name": "Bharath Gali ",
         "Company": "TD Bank",
         "Role": "Data Analyst Intern\/Co-op",
         "Date": "December 19th,2022",
         "InternshipDuration": "8",
         "Intake": "Fall 2022"
        },
        {
         "Name": "Vishnu Appala ",
         "Company": "TD Bank",
         "Role": "Data Analyst Intern\/Co-op",
         "Date": "December 19th,2022",
         "InternshipDuration": "4",
         "Intake": "Fall 2022"
        },
        {
         "Name": "Harkirat Singh Panesar ",
         "Company": "TD Bank",
         "Role": "Data Analyst Intern\/Co-op",
         "Date": "December 19th,2022",
         "InternshipDuration": "8",
         "Intake": "Fall 2022"
        },
        {
         "Name": "Krishna Sravanthi Telapudi",
         "Company": "TD Bank",
         "Role": "Data Analyst Intern\/Co-op",
         "Date": "December 19th,2022",
         "InternshipDuration": "4",
         "Intake": "Fall 2022"
        },
        {
         "Name": "Ahmed Abdullah ",
         "Company": "TD Bank",
         "Role": "Data Analyst Intern\/Co-op",
         "Date": "December 19th,2022",
         "InternshipDuration": "8",
         "Intake": "Fall 2022"
        },
        {
         "Name": "Dhaval Shirvi",
         "Company": "SOTI",
         "Role": "Performance Test Engineer",
         "Date": "December 19th,2022",
         "InternshipDuration": "4",
         "Intake": "Fall 2022"
        },
        {
         "Name": "Harsha Sai Rakesh Kumar Nalumachu ",
         "Company": "SOTI",
         "Role": "Performance Test Engineer",
         "Date": "December 19th,2022",
         "InternshipDuration": "4",
         "Intake": "Fall 2022"
        },
        {
         "Name": "Smitkumar Patel ",
         "Company": "Rocket Innovation Studio",
         "Role": "Software Developer",
         "Date": "December 19th,2022",
         "InternshipDuration": "8",
         "Intake": "Fall 2022"
        },
        {
         "Name": "Zeel Chamanbhai ",
         "Company": "SOTI",
         "Role": "Performance Test Engineer",
         "Date": "December 19th,2022",
         "InternshipDuration": "4",
         "Intake": "Fall 2022"
        },
        {
         "Name": "Tejbir Singh ",
         "Company": "SOTI",
         "Role": "Quality Assurance Specialist",
         "Date": "December 19th,2022",
         "InternshipDuration": "4",
         "Intake": "Fall 2022"
        },
        {
         "Name": "Prasham Ravi Thawani ",
         "Company": "SOTI",
         "Role": "Quality Assurance Specialist",
         "Date": "December 19th,2022",
         "InternshipDuration": "4",
         "Intake": "Fall 2022"
        },
        {
         "Name": "Megh Vijaybhai Patel ",
         "Company": "SOTI",
         "Role": "Quality Assurance Specialist",
         "Date": "December 19th,2022",
         "InternshipDuration": "8",
         "Intake": "Fall 2022"
        },
        {
         "Name": "Kenil Arvindbhai Maniya ",
         "Company": "SOTI",
         "Role": "Quality Assurance Specialist",
         "Date": "December 19th,2022",
         "InternshipDuration": "4",
         "Intake": "Fall 2022"
        },
        {
         "Name": "Alaknanda Faldu ",
         "Company": "SOTI",
         "Role": "Quality Assurance Specialist",
         "Date": "December 19th,2022",
         "InternshipDuration": "4",
         "Intake": "Fall 2022"
        },
        {
         "Name": "Sattvik Palta ",
         "Company": "SOTI",
         "Role": "Software Developer",
         "Date": "December 19th,2022",
         "InternshipDuration": "4",
         "Intake": "Fall 2022"
        },
        {
         "Name": "Kshitij Pandurang Halankar ",
         "Company": "SOTI",
         "Role": "Software Developer",
         "Date": "December 19th,2022",
         "InternshipDuration": "8",
         "Intake": "Fall 2022"
        },
        {
         "Name": "Shubham Taluja ",
         "Company": "SOTI",
         "Role": "Software Developer",
         "Date": "December 19th,2022",
         "InternshipDuration": "8",
         "Intake": "Fall 2022"
        },
        {
         "Name": "Darshil Shah ",
         "Company": "Ceridian",
         "Role": "Software Developer",
         "Date": "December 19th,2022",
         "InternshipDuration": "8",
         "Intake": "Fall 2022"
        },
        {
         "Name": "Anshul Chhabra ",
         "Company": "SOTI",
         "Role": "Software Developer",
         "Date": "December 19th,2022",
         "InternshipDuration": "4",
         "Intake": "Fall 2022"
        },
        {
         "Name": "Vendangkumar Vipulkumar Jotaniya ",
         "Company": "SOTI",
         "Role": "Software Developer",
         "Date": "December 19th,2022",
         "InternshipDuration": "8",
         "Intake": "Fall 2022"
        },
        {
         "Name": "Mrinal Walia ",
         "Company": "Loblaws Companies Ltd",
         "Role": "Data Scientist",
         "Date": "December 19th,2022",
         "InternshipDuration": "8",
         "Intake": "Fall 2022"
        },
        {
         "Name": "Anirudh Reddy Gotike ",
         "Company": "Sunlife",
         "Role": "Associate Software Engineer",
         "Date": "December 19th,2022",
         "InternshipDuration": "4",
         "Intake": "Fall 2022"
        },
        {
         "Name": "Nikita Hedaoo ",
         "Company": "Nokia",
         "Role": "Software Developer",
         "Date": "December 19th,2022",
         "InternshipDuration": "8",
         "Intake": "Fall 2022"
        },
        {
         "Name": "Parth Rameshbhai Patel ",
         "Company": "Nokia",
         "Role": "Software Developer",
         "Date": "December 19th,2022",
         "InternshipDuration": "4",
         "Intake": "Fall 2022"
        },
        {
         "Name": "Jomya Merlin George ",
         "Company": "Nokia",
         "Role": "Software Developer",
         "Date": "December 19th,2022",
         "InternshipDuration": "8",
         "Intake": "Fall 2022"
        },
        {
         "Name": "Syed Raazi Saeed ",
         "Company": "Nokia",
         "Role": "Software Developer",
         "Date": "December 19th,2022",
         "InternshipDuration": "4",
         "Intake": "Fall 2022"
        },
        {
         "Name": "Nishant Pansuriya ",
         "Company": "Nokia",
         "Role": "Project Management",
         "Date": "December 19th,2022",
         "InternshipDuration": "4",
         "Intake": "Fall 2022"
        },
        {
         "Name": "Noyal Sam Mathew ",
         "Company": "Nokia",
         "Role": "Robotic Process Automation Engineer",
         "Date": "December 19th,2022",
         "InternshipDuration": "8",
         "Intake": "Fall 2022"
        },
        {
         "Name": "Yash Vichare ",
         "Company": "CIBC",
         "Role": "Junior Application Developer ",
         "Date": "December 19th,2022",
         "InternshipDuration": "4",
         "Intake": "Fall 2022"
        },
        {
         "Name": "Dhrumil Parikh ",
         "Company": "CIBC",
         "Role": "Innovation engineer ",
         "Date": "December 19th,2022",
         "InternshipDuration": "8",
         "Intake": "Fall 2022"
        },
        {
         "Name": "Jijo Sabu ",
         "Company": "CIBC",
         "Role": "Data Science Developer",
         "Date": "December 19th,2022",
         "InternshipDuration": "4",
         "Intake": "Fall 2022"
        },
        {
         "Name": "Nishtha Patel ",
         "Company": "CIBC",
         "Role": "Junior Application Developer ",
         "Date": "December 19th,2022",
         "InternshipDuration": "8",
         "Intake": "Fall 2022"
        },
        {
         "Name": "Sai Kiran Beeravolu ",
         "Company": "CIBC",
         "Role": "AML Consultant",
         "Date": "December 19th,2022",
         "InternshipDuration": "4",
         "Intake": "Fall 2022"
        },
        {
         "Name": "Tanpreet Kaur ",
         "Company": "CIBC",
         "Role": "Production Application Support Analyst",
         "Date": "December 19th,2022",
         "InternshipDuration": "8",
         "Intake": "Fall 2022"
        },
        {
         "Name": "Jagjeet Singh ",
         "Company": "Softchoice",
         "Role": "Managed Service Case Analyst ",
         "Date": "December 19th,2022",
         "InternshipDuration": "4",
         "Intake": "Fall 2022"
        },
        {
         "Name": "Husain Handa",
         "Company": "Softchoice",
         "Role": "Workplace Solutions ",
         "Date": "December 19th,2022",
         "InternshipDuration": "4",
         "Intake": "Fall 2022"
        },
        {
         "Name": "Ifaz Mahmud ",
         "Company": "Softchoice",
         "Role": "Managed Service Case Analyst ",
         "Date": "December 19th,2022",
         "InternshipDuration": "4",
         "Intake": "Fall 2022"
        },
        {
         "Name": "Kathan Vaidya ",
         "Company": "BDO Canada LLP",
         "Role": "Software Engineer",
         "Date": "December 19th,2022",
         "InternshipDuration": "8",
         "Intake": "Fall 2022"
        },
        {
         "Name": "Manpreet Singh ",
         "Company": "BDO Canada LLP",
         "Role": "Software Engineer",
         "Date": "December 19th,2022",
         "InternshipDuration": "8",
         "Intake": "Fall 2022"
        },
        {
         "Name": "Babak Tajalli Nejad ",
         "Company": "BDO Canada LLP",
         "Role": "Full-stack Developer",
         "Date": "December 19th,2022",
         "InternshipDuration": "8",
         "Intake": "Fall 2022"
        },
        {
         "Name": "Lypsa Nirav Shah ",
         "Company": "BDO Canada LLP",
         "Role": "UI\/UX Design Analyst",
         "Date": "December 19th,2022",
         "InternshipDuration": "4",
         "Intake": "Fall 2022"
        },
        {
         "Name": "Piyush Mehta ",
         "Company": "BDO Canada LLP",
         "Role": "Full-stack Developer",
         "Date": "December 19th,2022",
         "InternshipDuration": "4",
         "Intake": "Fall 2022"
        },
        {
         "Name": "Abdul Hammad ",
         "Company": "BDO Canada LLP",
         "Role": "Quality\/Business Analyst",
         "Date": "December 19th,2022",
         "InternshipDuration": "4",
         "Intake": "Fall 2022"
        },
        {
         "Name": "Dimple Harshabhai Chandrani ",
         "Company": "Teqfocus",
         "Role": "Salesforce Developer Intern",
         "Date": "December 19th,2022",
         "InternshipDuration": "8",
         "Intake": "Fall 2022"
        },
        {
         "Name": "Nischay Dhiman ",
         "Company": "BlackBerry",
         "Role": "Software Developer",
         "Date": "December 19th,2022",
         "InternshipDuration": "8",
         "Intake": "Fall 2022"
        },
        {
         "Name": "Rohit Gupta",
         "Company": "BlackBerry",
         "Role": "Software Developer",
         "Date": "December 19th,2022",
         "InternshipDuration": "4",
         "Intake": "Fall 2022"
        },
        {
         "Name": "Darsh Divyeshkumar Desai ",
         "Company": "BlackBerry",
         "Role": "Release Engineer",
         "Date": "December 19th,2022",
         "InternshipDuration": "8",
         "Intake": "Fall 2022"
        },
        {
         "Name": "Hetansh Sharad Shah ",
         "Company": "BlackBerry",
         "Role": "Software Developer",
         "Date": "December 19th,2022",
         "InternshipDuration": "8",
         "Intake": "Fall 2022"
        },
        {
         "Name": "Prabhangad Singh ",
         "Company": "BlackBerry",
         "Role": "Software Developer",
         "Date": "December 19th,2022",
         "InternshipDuration": "4",
         "Intake": "Fall 2022"
        },
        {
         "Name": "Dheeraj Gavani ",
         "Company": "BlackBerry",
         "Role": "Software Developer",
         "Date": "December 19th,2022",
         "InternshipDuration": "4",
         "Intake": "Fall 2022"
        },
        {
         "Name": "Diksha ",
         "Company": "BlackBerry",
         "Role": "Software Developer",
         "Date": "December 19th,2022",
         "InternshipDuration": "8",
         "Intake": "Fall 2022"
        },
        {
         "Name": "Aburudh Mayuram",
         "Company": "BlackBerry",
         "Role": "Cyber Security Compliance Analyst",
         "Date": "December 19th,2022",
         "InternshipDuration": "8",
         "Intake": "Fall 2022"
        },
        {
         "Name": "Priyanka Munjal",
         "Company": "BlackBerry",
         "Role": "Software Automation Developer",
         "Date": "December 19th,2022",
         "InternshipDuration": "8",
         "Intake": "Fall 2022"
        },
        {
         "Name": "Archit Sehgal ",
         "Company": "BlackBerry",
         "Role": "Software Engineer",
         "Date": "December 19th,2022",
         "InternshipDuration": "8",
         "Intake": "Fall 2022"
        },
        {
         "Name": "Farhan Hammad ",
         "Company": "BlackBerry",
         "Role": "Application Engineer",
         "Date": "December 19th,2022",
         "InternshipDuration": "8",
         "Intake": "Fall 2022"
        },
        {
         "Name": "Kuldeep Rajeshkumar Panchal ",
         "Company": "BlackBerry",
         "Role": "Automation Test Development ",
         "Date": "December 19th,2022",
         "InternshipDuration": "8",
         "Intake": "Fall 2022"
        },
        {
         "Name": "Kshitiz Choudhary ",
         "Company": "BlackBerry",
         "Role": "Software Developer",
         "Date": "December 19th,2022",
         "InternshipDuration": "8",
         "Intake": "Fall 2022"
        },
        {
         "Name": "Venkata Keerthi Karnati ",
         "Company": "BlackBerry",
         "Role": "Software Test Specialist",
         "Date": "December 19th,2022",
         "InternshipDuration": "4",
         "Intake": "Fall 2022"
        },
        {
         "Name": "Avleen Kaur Mehna ",
         "Company": "BlackBerry",
         "Role": "Android Software Developer",
         "Date": "December 19th,2022",
         "InternshipDuration": "8",
         "Intake": "Fall 2022"
        },
        {
         "Name": "Harshavardhan Naidu Gangavarapu ",
         "Company": "BlackBerry",
         "Role": "Software Developer",
         "Date": "December 19th,2022",
         "InternshipDuration": "8",
         "Intake": "Fall 2022"
        },
        {
         "Name": "Prakruti Shantilal Vaghasiya ",
         "Company": "BlackBerry",
         "Role": "System Software Developer",
         "Date": "December 19th,2022",
         "InternshipDuration": "4",
         "Intake": "Fall 2022"
        },
        {
         "Name": "Namrata Vijaykumar Sanger ",
         "Company": "BlackBerry",
         "Role": "Software Developer",
         "Date": "December 19th,2022",
         "InternshipDuration": "8",
         "Intake": "Fall 2022"
        },
        {
         "Name": "Dhruv Sureshbhai Jasani ",
         "Company": "BlackBerry",
         "Role": "Salesforce Developer ",
         "Date": "December 19th,2022",
         "InternshipDuration": "4",
         "Intake": "Fall 2022"
        },
        {
         "Name": "Harsh Kamleshbhai Patel ",
         "Company": "BlackBerry",
         "Role": "Software Developer",
         "Date": "December 19th,2022",
         "InternshipDuration": "4",
         "Intake": "Fall 2022"
        },
        {
         "Name": "Varshesh Patel ",
         "Company": "RBC",
         "Role": "Software Developer",
         "Date": "December 19th,2022",
         "InternshipDuration": "8",
         "Intake": "Fall 2022"
        },
        {
         "Name": "Jay Paresh Patel ",
         "Company": "RBC",
         "Role": "Software Developer",
         "Date": "December 19th,2022",
         "InternshipDuration": "8",
         "Intake": "Fall 2022"
        },
        {
         "Name": "Yah Chavda ",
         "Company": "RBC",
         "Role": "Software Developer",
         "Date": "December 19th,2022",
         "InternshipDuration": "8",
         "Intake": "Fall 2022"
        },
        {
         "Name": "Ashutosh Sadana",
         "Company": "RBC",
         "Role": "Cyber Security ",
         "Date": "December 19th,2022",
         "InternshipDuration": "8",
         "Intake": "Fall 2022"
        },
        {
         "Name": "Ayushi Patel ",
         "Company": "RBC",
         "Role": "Operation analyst",
         "Date": "December 19th,2022",
         "InternshipDuration": "8",
         "Intake": "Fall 2022"
        },
        {
         "Name": "Varshitha Seralathan ",
         "Company": "RBC",
         "Role": "Software Developer",
         "Date": "December 19th,2022",
         "InternshipDuration": "8",
         "Intake": "Fall 2022"
        },
        {
         "Name": "Karanjot Singh ",
         "Company": "RBC",
         "Role": "Data Analyst Intern",
         "Date": "December 19th,2022",
         "InternshipDuration": "8",
         "Intake": "Fall 2022"
        },
        {
         "Name": "Kartik Peddinti ",
         "Company": "RBC",
         "Role": "Capital Markets ",
         "Date": "December 19th,2022",
         "InternshipDuration": "8",
         "Intake": "Fall 2022"
        },
        {
         "Name": "Jinalben Nikunjbhai Ka Patel ",
         "Company": "RBC",
         "Role": "Capital Markets ",
         "Date": "December 19th,2022",
         "InternshipDuration": "4",
         "Intake": "Fall 2022"
        },
        {
         "Name": "Aishwarya Reddy Mannem ",
         "Company": "RBC",
         "Role": "Software Developer",
         "Date": "December 19th,2022",
         "InternshipDuration": "8",
         "Intake": "Fall 2022"
        },
        {
         "Name": "Lakshika Anand ",
         "Company": "RBC",
         "Role": "Quality Engineering",
         "Date": "December 19th,2022",
         "InternshipDuration": "4",
         "Intake": "Fall 2022"
        },
        {
         "Name": "Abhee Baboo Hudani ",
         "Company": "RBC",
         "Role": "Software Developer",
         "Date": "December 19th,2022",
         "InternshipDuration": "4",
         "Intake": "Fall 2022"
        },
        {
         "Name": "Ekta Kaushik ",
         "Company": "RBC",
         "Role": "Software Developer",
         "Date": "December 19th,2022",
         "InternshipDuration": "8",
         "Intake": "Fall 2022"
        },
        {
         "Name": "Jaineel Fenal Dharia ",
         "Company": "RBC",
         "Role": "Business System Analyst",
         "Date": "December 19th,2022",
         "InternshipDuration": "4",
         "Intake": "Fall 2022"
        },
        {
         "Name": "Asmita Kaushal ",
         "Company": "RBC",
         "Role": "Business System Analyst",
         "Date": "December 19th,2022",
         "InternshipDuration": "4",
         "Intake": "Fall 2022"
        },
        {
         "Name": "Varshesh Patel ",
         "Company": "RBC",
         "Role": "Software Developer",
         "Date": "December 19th,2022",
         "InternshipDuration": "4",
         "Intake": "Fall 2022"
        },
        {
         "Name": "Jay Paresh Patel ",
         "Company": "RBC",
         "Role": "DevOps Engineer",
         "Date": "December 19th,2022",
         "InternshipDuration": "8",
         "Intake": "Fall 2022"
        },
        {
         "Name": "Sandhya Bharatbhai Ramoliya ",
         "Company": "BMO",
         "Role": "Big Data ",
         "Date": "December 19th,2022",
         "InternshipDuration": "4",
         "Intake": "Fall 2022"
        },
        {
         "Name": "Dwija Patel ",
         "Company": "BMO",
         "Role": "Quality Assurance Analyst",
         "Date": "December 19th,2022",
         "InternshipDuration": "8",
         "Intake": "Fall 2022"
        },
        {
         "Name": "Vraj Shah",
         "Company": "BMO",
         "Role": "Business System Analyst",
         "Date": "December 19th,2022",
         "InternshipDuration": "4",
         "Intake": "Fall 2022"
        },
        {
         "Name": "Sahitya Chowdary Yaganti ",
         "Company": "BMO",
         "Role": "Application Engineer",
         "Date": "December 19th,2022",
         "InternshipDuration": "4",
         "Intake": "Fall 2022"
        },
        {
         "Name": "Riya Manishbhai Bhavsar ",
         "Company": "BMO",
         "Role": "Project Management",
         "Date": "December 19th,2022",
         "InternshipDuration": "8",
         "Intake": "Fall 2022"
        },
        {
         "Name": "Karishma Chowdary Cherukuri ",
         "Company": "Bell Canada",
         "Role": "Software Developer",
         "Date": "December 19th,2022",
         "InternshipDuration": "4",
         "Intake": "Fall 2022"
        },
        {
         "Name": "Madhumita Shankar ",
         "Company": "IBM",
         "Role": "Software Engineer",
         "Date": "December 19th,2022",
         "InternshipDuration": "8",
         "Intake": "Fall 2022"
        },
        {
         "Name": "Shardul Yadav ",
         "Company": "IBM",
         "Role": "DevOps Engineer",
         "Date": "December 19th,2022",
         "InternshipDuration": "8",
         "Intake": "Fall 2022"
        },
        {
         "Name": "Adnan Ali Gulegulzar ",
         "Company": "Caseware",
         "Role": "Software Developer",
         "Date": "December 19th,2022",
         "InternshipDuration": "8",
         "Intake": "Fall 2022"
        },
        {
         "Name": "Mudita Sharma",
         "Company": "ScotiaBank",
         "Role": "Project Management",
         "Date": "December 19th,2022",
         "InternshipDuration": "8",
         "Intake": "Fall 2022"
        },
        {
         "Name": "Rakshana Bagavathi ",
         "Company": "ScotiaBank",
         "Role": "Data Scientist",
         "Date": "December 19th,2022",
         "InternshipDuration": "8",
         "Intake": "Fall 2022"
        },
        {
         "Name": "Nethra Bangalore Vijayadas ",
         "Company": "ScotiaBank",
         "Role": "Software Engineer",
         "Date": "December 19th,2022",
         "InternshipDuration": "8",
         "Intake": "Fall 2022"
        },
        {
         "Name": "Deep Shailesh Bhai Roval ",
         "Company": "ScotiaBank",
         "Role": "Software Engineer",
         "Date": "December 19th,2022",
         "InternshipDuration": "8",
         "Intake": "Fall 2022"
        },
        {
         "Name": "Swaroop Somashekhar Mensinkai ",
         "Company": "Healthcare Ontario Pension",
         "Role": "Data Scientist",
         "Date": "December 19th,2022",
         "InternshipDuration": "4",
         "Intake": "Fall 2022"
        },
        {
         "Name": "Akshaya Muthuraman ",
         "Company": "Nuance",
         "Role": "Data Scientist",
         "Date": "December 19th,2022",
         "InternshipDuration": "8",
         "Intake": "Fall 2022"
        }
 ]